helper/__init__.py
helper/data.py
helper/default.toml
helper/handlers.py
helper/helper.py
helper/misc.py
helper/pandas.py
helper/util.py
jupyter_helper-0.0.1.post3.dist-info/LICENSE
jupyter_helper-0.0.1.post3.dist-info/METADATA
jupyter_helper-0.0.1.post3.dist-info/WHEEL
jupyter_helper-0.0.1.post3.dist-info/top_level.txt
jupyter_helper-0.0.1.post3.dist-info/RECORD
