Metadata-Version: 2.1
Name: jupyter-helper
Version: 0.0.1.post3
Summary: A helper for jupyter(lab/notebook/console)
Author-email: Lilin Lao <lll9p.china@gmail.com>
License: MIT
Project-URL: homepage, https://github.com/lll9p/jupyter-helper
Project-URL: repository, https://github.com/lll9p/jupyter-helper
Keywords: jupyter,helper,ipython
Classifier: Programming Language :: Python :: 3
Classifier: License :: OSI Approved :: MIT License
Classifier: Operating System :: OS Independent
Requires-Python: >=3.10
License-File: LICENSE
Requires-Dist: ipython
Requires-Dist: pandas
